{
  "items": [
    {
      "numericId": 1,
      "id": "ascension_1",
      "nameKey": "ascension.1.name",
      "descriptionKey": "ascension.1.desc",
      "upgradeIds": ["map_more_unknown_nodes"]
    },
    {
      "numericId": 2,
      "id": "ascension_2",
      "nameKey": "ascension.2.name",
      "descriptionKey": "ascension.2.desc",
      "upgradeIds": ["map_more_enemy_nodes"]
    },
    {
      "numericId": 3,
      "id": "ascension_3",
      "nameKey": "ascension.3.name",
      "descriptionKey": "ascension.3.desc",
      "upgradeIds": ["player_max_health_minus_5"]
    },
    {
      "numericId": 4,
      "id": "ascension_4",
      "nameKey": "ascension.4.name",
      "descriptionKey": "ascension.4.desc",
      "upgradeIds": ["starting_deck_add_basic_directions"]
    },
    {
      "numericId": 5,
      "id": "ascension_5",
      "nameKey": "ascension.5.name",
      "descriptionKey": "ascension.5.desc",
      "upgradeIds": ["gold_gain_80"]
    },
    {
      "numericId": 6,
      "id": "ascension_6",
      "nameKey": "ascension.6.name",
      "descriptionKey": "ascension.6.desc",
      "upgradeIds": ["reward_magic_choices_minus_1"]
    },
    {
      "numericId": 7,
      "id": "ascension_7",
      "nameKey": "ascension.7.name",
      "descriptionKey": "ascension.7.desc",
      "upgradeIds": ["starting_magic_slots_minus_2_a7"]
    },
    {
      "numericId": 8,
      "id": "ascension_8",
      "nameKey": "ascension.8.name",
      "descriptionKey": "ascension.8.desc",
      "upgradeIds": ["map_block_cells_plus_1_a8"]
    },
    {
      "numericId": 9,
      "id": "ascension_9",
      "nameKey": "ascension.9.name",
      "descriptionKey": "ascension.9.desc",
      "upgradeIds": ["starting_deck_add_placeholder"]
    },
    {
      "numericId": 10,
      "id": "ascension_10",
      "nameKey": "ascension.10.name",
      "descriptionKey": "ascension.10.desc",
      "upgradeIds": ["shop_price_120"]
    },
    {
      "numericId": 11,
      "id": "ascension_11",
      "nameKey": "ascension.11.name",
      "descriptionKey": "ascension.11.desc",
      "upgradeIds": ["rare_magic_less_common"]
    },
    {
      "numericId": 12,
      "id": "ascension_12",
      "nameKey": "ascension.12.name",
      "descriptionKey": "ascension.12.desc",
      "upgradeIds": ["map_smaller"]
    },
    {
      "numericId": 13,
      "id": "ascension_13",
      "nameKey": "ascension.13.name",
      "descriptionKey": "ascension.13.desc",
      "upgradeIds": ["starting_magic_slots_minus_1_a13"]
    },
    {
      "numericId": 14,
      "id": "ascension_14",
      "nameKey": "ascension.14.name",
      "descriptionKey": "ascension.14.desc",
      "upgradeIds": ["enemy_health_20"]
    },
    {
      "numericId": 15,
      "id": "ascension_15",
      "nameKey": "ascension.15.name",
      "descriptionKey": "ascension.15.desc",
      "upgradeIds": ["level_cap_minus_4"]
    },
    {
      "numericId": 16,
      "id": "ascension_16",
      "nameKey": "ascension.16.name",
      "descriptionKey": "ascension.16.desc",
      "upgradeIds": ["map_block_cells_plus_1"]
    },
    {
      "numericId": 17,
      "id": "ascension_17",
      "nameKey": "ascension.17.name",
      "descriptionKey": "ascension.17.desc",
      "upgradeIds": ["enemy_attack_intents_20"]
    },
    {
      "numericId": 18,
      "id": "ascension_18",
      "nameKey": "ascension.18.name",
      "descriptionKey": "ascension.18.desc",
      "upgradeIds": ["rest_nodes_less_common"]
    },
    {
      "numericId": 19,
      "id": "ascension_19",
      "nameKey": "ascension.19.name",
      "descriptionKey": "ascension.19.desc",
      "upgradeIds": ["level_cap_minus_2"]
    },
    {
      "numericId": 20,
      "id": "ascension_20",
      "nameKey": "ascension.20.name",
      "descriptionKey": "ascension.20.desc",
      "upgradeIds": ["boss_harder"]
    },
    {
      "numericId": -1,
      "id": "ascension_minus_1",
      "nameKey": "ascension.minus_1.name",
      "descriptionKey": "ascension.minus_1.desc",
      "upgradeIds": ["player_base_draw_count_plus_1"]
    },
    {
      "numericId": -2,
      "id": "ascension_minus_2",
      "nameKey": "ascension.minus_2.name",
      "descriptionKey": "ascension.minus_2.desc",
      "upgradeIds": ["designed_battle_count_minus_1"]
    },
    {
      "numericId": -3,
      "id": "ascension_minus_3",
      "nameKey": "ascension.minus_3.name",
      "descriptionKey": "ascension.minus_3.desc",
      "upgradeIds": ["player_max_health_plus_5"]
    },
    {
      "numericId": -4,
      "id": "ascension_minus_4",
      "nameKey": "ascension.minus_4.name",
      "descriptionKey": "ascension.minus_4.desc",
      "upgradeIds": ["starting_deck_add_omni_arrow"]
    },
    {
      "numericId": -5,
      "id": "ascension_minus_5",
      "nameKey": "ascension.minus_5.name",
      "descriptionKey": "ascension.minus_5.desc",
      "upgradeIds": ["gold_gain_125"]
    },
    {
      "numericId": -6,
      "id": "ascension_minus_6",
      "nameKey": "ascension.minus_6.name",
      "descriptionKey": "ascension.minus_6.desc",
      "upgradeIds": ["reward_magic_choices_plus_1"]
    },
    {
      "numericId": -7,
      "id": "ascension_minus_7",
      "nameKey": "ascension.minus_7.name",
      "descriptionKey": "ascension.minus_7.desc",
      "upgradeIds": ["starting_magic_slots_plus_1_a7"]
    },
    {
      "numericId": -8,
      "id": "ascension_minus_8",
      "nameKey": "ascension.minus_8.name",
      "descriptionKey": "ascension.minus_8.desc",
      "upgradeIds": ["designed_event_count_plus_1"]
    },
    {
      "numericId": -9,
      "id": "ascension_minus_9",
      "nameKey": "ascension.minus_9.name",
      "descriptionKey": "ascension.minus_9.desc",
      "upgradeIds": ["starting_deck_add_three_random_doubled"]
    },
    {
      "numericId": -10,
      "id": "ascension_minus_10",
      "nameKey": "ascension.minus_10.name",
      "descriptionKey": "ascension.minus_10.desc",
      "upgradeIds": ["shop_price_50"]
    },
    {
      "numericId": -11,
      "id": "ascension_minus_11",
      "nameKey": "ascension.minus_11.name",
      "descriptionKey": "ascension.minus_11.desc",
      "upgradeIds": ["elite_guaranteed_legendary"]
    },
    {
      "numericId": -12,
      "id": "ascension_minus_12",
      "nameKey": "ascension.minus_12.name",
      "descriptionKey": "ascension.minus_12.desc",
      "upgradeIds": ["designed_map_main_area_height_plus_1"]
    },
    {
      "numericId": -13,
      "id": "ascension_minus_13",
      "nameKey": "ascension.minus_13.name",
      "descriptionKey": "ascension.minus_13.desc",
      "upgradeIds": ["starting_magic_slots_plus_1_a13"]
    },
    {
      "numericId": -14,
      "id": "ascension_minus_14",
      "nameKey": "ascension.minus_14.name",
      "descriptionKey": "ascension.minus_14.desc",
      "upgradeIds": ["enemy_initial_vulnerable_4"]
    },
    {
      "numericId": -15,
      "id": "ascension_minus_15",
      "nameKey": "ascension.minus_15.name",
      "descriptionKey": "ascension.minus_15.desc",
      "upgradeIds": ["chapter_length_plus_2_a15"]
    },
    {
      "numericId": -16,
      "id": "ascension_minus_16",
      "nameKey": "ascension.minus_16.name",
      "descriptionKey": "ascension.minus_16.desc",
      "upgradeIds": ["designed_reward_count_plus_1"]
    },
    {
      "numericId": -17,
      "id": "ascension_minus_17",
      "nameKey": "ascension.minus_17.name",
      "descriptionKey": "ascension.minus_17.desc",
      "upgradeIds": ["enemy_initial_weak_6"]
    },
    {
      "numericId": -18,
      "id": "ascension_minus_18",
      "nameKey": "ascension.minus_18.name",
      "descriptionKey": "ascension.minus_18.desc",
      "upgradeIds": ["designed_rest_count_plus_1"]
    },
    {
      "numericId": -19,
      "id": "ascension_minus_19",
      "nameKey": "ascension.minus_19.name",
      "descriptionKey": "ascension.minus_19.desc",
      "upgradeIds": ["chapter_length_plus_2_a19"]
    },
    {
      "numericId": -20,
      "id": "ascension_minus_20",
      "nameKey": "ascension.minus_20.name",
      "descriptionKey": "ascension.minus_20.desc",
      "upgradeIds": ["extra_top_boss_cells_2"]
    }
  ]
}
